{
	"credit": "Made with Blockbench by yungwilder",
	"texture_size": [32, 32],
	"textures": {
		"0": "item/cosmic21/galaxy_glaive",
		"particle": "item/cosmic21/galaxy_glaive"
	},
	"elements": [
		{
			"name": "blade",
			"from": [8.5, 13, 5],
			"to": [8.5, 32, 14],
			"rotation": {"angle": 0, "axis": "y", "origin": [16, 39, 16]},
			"faces": {
				"north": {"uv": [0, 0, 0, 8], "texture": "#0"},
				"east": {"uv": [4.5, 4.5, 9, 14], "texture": "#0"},
				"south": {"uv": [0, 0, 0, 8], "texture": "#0"},
				"west": {"uv": [9, 4.5, 4.5, 14], "texture": "#0"},
				"up": {"uv": [0, 4.5, 0, 0], "texture": "#0"},
				"down": {"uv": [0, 0, 0, 4.5], "texture": "#0"}
			}
		},
		{
			"from": [8, 17, 6],
			"to": [9, 21, 7],
			"rotation": {"angle": 0, "axis": "y", "origin": [16, 40, 15]},
			"faces": {
				"north": {"uv": [4.5, 2.5, 5, 4.5], "texture": "#0"},
				"east": {"uv": [5, 2.5, 5.5, 4.5], "texture": "#0"},
				"south": {"uv": [5.5, 2.5, 6, 4.5], "texture": "#0"},
				"west": {"uv": [6, 2.5, 6.5, 4.5], "texture": "#0"},
				"up": {"uv": [4.5, 11, 4, 10.5], "texture": "#0"},
				"down": {"uv": [9.5, 10.5, 9, 11], "texture": "#0"}
			}
		},
		{
			"from": [8, 15, 9],
			"to": [9, 17, 10],
			"rotation": {"angle": 0, "axis": "y", "origin": [16, 36, 18]},
			"faces": {
				"north": {"uv": [9.5, 5, 10, 6], "texture": "#0"},
				"east": {"uv": [9.5, 6, 10, 7], "texture": "#0"},
				"south": {"uv": [9.5, 7, 10, 8], "texture": "#0"},
				"west": {"uv": [9.5, 8, 10, 9], "texture": "#0"},
				"up": {"uv": [11, 11, 10.5, 10.5], "texture": "#0"},
				"down": {"uv": [11, 3, 10.5, 3.5], "texture": "#0"}
			}
		},
		{
			"from": [8, 17, 7],
			"to": [9, 19, 8],
			"rotation": {"angle": 0, "axis": "y", "origin": [16, 42, 15]},
			"faces": {
				"north": {"uv": [10, 5, 10.5, 5.5], "texture": "#0"},
				"east": {"uv": [10, 5.5, 10.5, 6], "texture": "#0"},
				"south": {"uv": [10, 6, 10.5, 6.5], "texture": "#0"},
				"west": {"uv": [10, 6.5, 10.5, 7], "texture": "#0"},
				"up": {"uv": [10.5, 7.5, 10, 7], "texture": "#0"},
				"down": {"uv": [10.5, 7.5, 10, 8], "texture": "#0"}
			}
		},
		{
			"from": [8, 18, 8],
			"to": [9, 20, 9],
			"rotation": {"angle": 0, "axis": "y", "origin": [16, 42, 16]},
			"faces": {
				"north": {"uv": [9.5, 1, 10, 2], "texture": "#0"},
				"east": {"uv": [9.5, 2, 10, 3], "texture": "#0"},
				"south": {"uv": [9.5, 3, 10, 4], "texture": "#0"},
				"west": {"uv": [9.5, 4, 10, 5], "texture": "#0"},
				"up": {"uv": [10, 11, 9.5, 10.5], "texture": "#0"},
				"down": {"uv": [10.5, 10.5, 10, 11], "texture": "#0"}
			}
		},
		{
			"from": [8, 20, 7],
			"to": [9, 21, 10],
			"rotation": {"angle": 0, "axis": "y", "origin": [16, 43, 18]},
			"faces": {
				"north": {"uv": [3, 10.5, 3.5, 11], "texture": "#0"},
				"east": {"uv": [6.5, 4, 8, 4.5], "texture": "#0"},
				"south": {"uv": [3.5, 10.5, 4, 11], "texture": "#0"},
				"west": {"uv": [8, 4, 9.5, 4.5], "texture": "#0"},
				"up": {"uv": [4.5, 10.5, 4, 9], "texture": "#0"},
				"down": {"uv": [9.5, 9, 9, 10.5], "texture": "#0"}
			}
		},
		{
			"from": [8, 21, 7],
			"to": [9, 26, 9],
			"rotation": {"angle": 0, "axis": "y", "origin": [16, 45, 17]},
			"faces": {
				"north": {"uv": [2.5, 8, 3, 10.5], "texture": "#0"},
				"east": {"uv": [4.5, 0, 5.5, 2.5], "texture": "#0"},
				"south": {"uv": [3, 8, 3.5, 10.5], "texture": "#0"},
				"west": {"uv": [5.5, 0, 6.5, 2.5], "texture": "#0"},
				"up": {"uv": [9.5, 1, 9, 0], "texture": "#0"},
				"down": {"uv": [9.5, 1, 9, 2], "texture": "#0"}
			}
		},
		{
			"from": [8, 22, 9],
			"to": [9, 24, 10],
			"rotation": {"angle": 0, "axis": "y", "origin": [16, 46, 18]},
			"faces": {
				"north": {"uv": [9, 6.5, 9.5, 7.5], "texture": "#0"},
				"east": {"uv": [9, 7.5, 9.5, 8.5], "texture": "#0"},
				"south": {"uv": [9.5, 9.5, 10, 10.5], "texture": "#0"},
				"west": {"uv": [9.5, 0, 10, 1], "texture": "#0"},
				"up": {"uv": [10.5, 10, 10, 9.5], "texture": "#0"},
				"down": {"uv": [3, 10.5, 2.5, 11], "texture": "#0"}
			}
		},
		{
			"from": [8, 26, 8],
			"to": [9, 28, 9],
			"rotation": {"angle": 0, "axis": "y", "origin": [16, 50, 17]},
			"faces": {
				"north": {"uv": [9, 2, 9.5, 3], "texture": "#0"},
				"east": {"uv": [9, 3, 9.5, 4], "texture": "#0"},
				"south": {"uv": [9, 4.5, 9.5, 5.5], "texture": "#0"},
				"west": {"uv": [9, 5.5, 9.5, 6.5], "texture": "#0"},
				"up": {"uv": [10.5, 8.5, 10, 8], "texture": "#0"},
				"down": {"uv": [10.5, 8.5, 10, 9], "texture": "#0"}
			}
		},
		{
			"from": [8, -14, 8],
			"to": [9, -11, 9],
			"rotation": {"angle": 0, "axis": "y", "origin": [16, -4, 16]},
			"faces": {
				"north": {"uv": [8, 1, 8.5, 2.5], "texture": "#0"},
				"east": {"uv": [8.5, 1, 9, 2.5], "texture": "#0"},
				"south": {"uv": [8.5, 2.5, 9, 4], "texture": "#0"},
				"west": {"uv": [3.5, 9, 4, 10.5], "texture": "#0"},
				"up": {"uv": [10.5, 3.5, 10, 3], "texture": "#0"},
				"down": {"uv": [10.5, 3.5, 10, 4], "texture": "#0"}
			}
		},
		{
			"from": [7.5, -11, 7.5],
			"to": [9.5, -10, 9.5],
			"rotation": {"angle": 0, "axis": "y", "origin": [16, -1, 17]},
			"faces": {
				"north": {"uv": [9.5, 9, 10.5, 9.5], "texture": "#0"},
				"east": {"uv": [10, 10, 11, 10.5], "texture": "#0"},
				"south": {"uv": [10, 0, 11, 0.5], "texture": "#0"},
				"west": {"uv": [10, 0.5, 11, 1], "texture": "#0"},
				"up": {"uv": [7.5, 4, 6.5, 3], "texture": "#0"},
				"down": {"uv": [8.5, 3, 7.5, 4], "texture": "#0"}
			}
		},
		{
			"from": [7.5, -15, 7.5],
			"to": [9.5, -14, 9.5],
			"rotation": {"angle": 0, "axis": "y", "origin": [16, -5, 17]},
			"faces": {
				"north": {"uv": [10, 1, 11, 1.5], "texture": "#0"},
				"east": {"uv": [10, 1.5, 11, 2], "texture": "#0"},
				"south": {"uv": [10, 2, 11, 2.5], "texture": "#0"},
				"west": {"uv": [10, 2.5, 11, 3], "texture": "#0"},
				"up": {"uv": [4.5, 9, 3.5, 8], "texture": "#0"},
				"down": {"uv": [9, 0, 8, 1], "texture": "#0"}
			}
		},
		{
			"from": [8, 1, 8],
			"to": [9, 17, 9],
			"rotation": {"angle": 0, "axis": "y", "origin": [16, 25, 16]},
			"faces": {
				"north": {"uv": [0, 8, 0.5, 16], "texture": "#0"},
				"east": {"uv": [0.5, 8, 1, 16], "texture": "#0"},
				"south": {"uv": [1, 8, 1.5, 16], "texture": "#0"},
				"west": {"uv": [1.5, 8, 2, 16], "texture": "#0"},
				"up": {"uv": [10.5, 4.5, 10, 4], "texture": "#0"},
				"down": {"uv": [10.5, 4.5, 10, 5], "texture": "#0"}
			}
		},
		{
			"from": [8, -4, 8],
			"to": [9, 1, 9],
			"rotation": {"angle": 0, "axis": "y", "origin": [16, 19, 16]},
			"faces": {
				"north": {"uv": [0.5, 13.5, 1, 16], "texture": "#0"},
				"east": {"uv": [0.5, 13.5, 1, 16], "texture": "#0"},
				"south": {"uv": [0.5, 13.5, 1, 16], "texture": "#0"},
				"west": {"uv": [0.5, 13.5, 1, 16], "texture": "#0"},
				"up": {"uv": [0.5, 13.5, 1, 16], "texture": "#0"},
				"down": {"uv": [0.5, 13.5, 1, 16], "texture": "#0"}
			}
		},
		{
			"from": [8, -10, 8],
			"to": [9, -4, 9],
			"rotation": {"angle": 0, "axis": "y", "origin": [16, 4, 16]},
			"faces": {
				"north": {"uv": [6.5, 0, 7, 3], "texture": "#0"},
				"east": {"uv": [7, 0, 7.5, 3], "texture": "#0"},
				"south": {"uv": [7.5, 0, 8, 3], "texture": "#0"},
				"west": {"uv": [2, 8, 2.5, 11], "texture": "#0"},
				"up": {"uv": [8.5, 3, 8, 2.5], "texture": "#0"},
				"down": {"uv": [9.5, 8.5, 9, 9], "texture": "#0"}
			}
		}
	],
	"gui_light": "front",
	"display": {
		"thirdperson_righthand": {
			"rotation": [0, -180, 0],
			"translation": [0.5, 5, 1.5]
		},
		"thirdperson_lefthand": {
			"rotation": [0, -180, 0],
			"translation": [-0.5, 5, 1.5]
		},
		"firstperson_righthand": {
			"rotation": [-45, -180, 0],
			"translation": [6, 0, 0],
			"scale": [0.75, 0.75, 0.75]
		},
		"firstperson_lefthand": {
			"rotation": [-45, -180, 0],
			"translation": [6, 0, 0],
			"scale": [0.75, 0.75, 0.75]
		},
		"ground": {
			"rotation": [45, 45, 0],
			"translation": [0, 5.25, 0],
			"scale": [0.5, 0.5, 0.5]
		},
		"gui": {
			"rotation": [-90, 135, 90],
			"scale": [0.4, 0.4, 0.4]
		},
		"head": {
			"rotation": [90, -45, 90],
			"scale": [0.36, 0.36, 0.36]
		},
		"fixed": {
			"rotation": [90, -45, 90],
			"translation": [0.25, 0, -0.75],
			"scale": [0.55, 0.55, 0.55]
		}
	},
	"groups": [0,
		{
			"name": "guard",
			"origin": [16, 44, 17],
			"children": [1, 2, 3, 4, 5, 6, 7, 8]
		},
		{
			"name": "bottom handle",
			"origin": [16, -6, 17],
			"children": [9, 10, 11]
		},
		{
			"name": "handle",
			"origin": [16, 3, 16],
			"children": [12, 13, 14]
		}
	]
}